hpc_acm/3rdpartylicenses.txt
hpc_acm/__init__.py
hpc_acm/api_client.py
hpc_acm/configuration.py
hpc_acm/rest.py
hpc_acm/api/__init__.py
hpc_acm/api/default_api.py
hpc_acm/models/__init__.py
hpc_acm/models/diagnotic_test.py
hpc_acm/models/event.py
hpc_acm/models/ip_v4.py
hpc_acm/models/ip_v6.py
hpc_acm/models/job.py
hpc_acm/models/job_state.py
hpc_acm/models/job_summary.py
hpc_acm/models/job_type.py
hpc_acm/models/job_update.py
hpc_acm/models/mac_address.py
hpc_acm/models/metrics.py
hpc_acm/models/metrics_values.py
hpc_acm/models/node.py
hpc_acm/models/node_gpu.py
hpc_acm/models/node_job.py
hpc_acm/models/node_metadata.py
hpc_acm/models/node_metadata_compute.py
hpc_acm/models/node_metadata_network.py
hpc_acm/models/node_metadata_network_interface.py
hpc_acm/models/node_metadata_network_ipv4.py
hpc_acm/models/node_metadata_network_ipv4_ip_address.py
hpc_acm/models/node_metadata_network_ipv4_subnet.py
hpc_acm/models/node_metadata_network_ipv6.py
hpc_acm/models/node_metrics.py
hpc_acm/models/node_metrics_data.py
hpc_acm/models/node_metrics_metric_items.py
hpc_acm/models/node_network.py
hpc_acm/models/node_registration.py
hpc_acm/models/node_summary.py
hpc_acm/models/scheduled_event.py
hpc_acm/models/scheduled_events.py
hpc_acm/models/task.py
hpc_acm/models/task_output.py
hpc_acm/models/task_result.py
hpc_acm/models/task_state.py
hpc_acm-1.3.1.dist-info/DESCRIPTION.rst
hpc_acm-1.3.1.dist-info/METADATA
hpc_acm-1.3.1.dist-info/RECORD
hpc_acm-1.3.1.dist-info/WHEEL
hpc_acm-1.3.1.dist-info/metadata.json
hpc_acm-1.3.1.dist-info/top_level.txt
test/__init__.py
test/test_default_api.py
test/test_diagnotic_test.py
test/test_event.py
test/test_ip_v4.py
test/test_ip_v6.py
test/test_job.py
test/test_job_state.py
test/test_job_summary.py
test/test_job_type.py
test/test_job_update.py
test/test_mac_address.py
test/test_metrics.py
test/test_metrics_values.py
test/test_node.py
test/test_node_gpu.py
test/test_node_job.py
test/test_node_metadata.py
test/test_node_metadata_compute.py
test/test_node_metadata_network.py
test/test_node_metadata_network_interface.py
test/test_node_metadata_network_ipv4.py
